{
  "resources": [
    {
      "path": "data.csv",
      "name": "data",
      "profile": "tabular-data-resource",
      "scheme": "file",
      "format": "csv",
      "hashing": "md5",
      "encoding": "utf-8",
      "schema": {
        "fields": [
          {
            "name": "Year",
            "type": "integer",
            "title": "Jahr"
          },
          {
            "name": "Region",
            "type": "string",
            "constraints": {
              "enum": [
                "Enzkreis",
                "Land BW",
                ""
              ]
            },
            "title": "Region"
          },
          {
            "name": "Value",
            "type": "integer",
            "title": "Value"
          }
        ]
      }
    }
  ],
  "profile": "data-package",
  "name": "5-2",
  "title": "Anteil der Frauen und M채dchen im Alter von 15 Jahren und 채lter, die sich in ihrer jetzigen oder fr체heren Partnerschaft physischer, sexueller oder psychischer Gewalt durch ihren aktuellen oder fr체heren Intimpartner in den vergangenen 12 Monaten ausgesetzt waren, nach Art der Gewalt und Alter"
}